HISTORY.rst
LICENSE
MANIFEST.in
README.rst
flask_pjax.py
setup.py
Flask_PJAX.egg-info/PKG-INFO
Flask_PJAX.egg-info/SOURCES.txt
Flask_PJAX.egg-info/dependency_links.txt
Flask_PJAX.egg-info/not-zip-safe
Flask_PJAX.egg-info/requires.txt
Flask_PJAX.egg-info/top_level.txt