Metadata-Version: 1.1
Name: Flask-PJAX
Version: 0.0.1
Summary: PJAX Templating for Flask Applications
Home-page: http://github.com/rhyselsmore/flask-pjax
Author: Rhys Elsmore
Author-email: me@rhys.io
License: Copyright 2013 Rhys Elsmore
